setup.py
geforce/__init__.py
geforce.egg-info/PKG-INFO
geforce.egg-info/SOURCES.txt
geforce.egg-info/dependency_links.txt
geforce.egg-info/top_level.txt